{
  "race": "Daytona 500",
  "stage1": [
    { "driver": "Denny Hamlin", "position": 1, "points": 10 },
    { "driver": "Kyle Busch", "position": 2, "points": 9 },
    { "driver": "Brad Keselowski", "position": 3, "points": 8 },
    { "driver": "Austin Cindric", "position": 4, "points": 7 },
    { "driver": "William Byron", "position": 5, "points": 6 },
    { "driver": "Matt Kenseth", "position": 6, "points": 5 },
    { "driver": "Joey Logano", "position": 7, "points": 4 },
    { "driver": "Greg Biffle", "position": 8, "points": 3 },
    { "driver": "Kevin Harvick", "position": 9, "points": 2 },
    { "driver": "Ryan Newman", "position": 10, "points": 1 }
  ],
  "stage2": [
    { "driver": "Matt Kenseth", "position": 1, "points": 10 },
    { "driver": "William Byron", "position": 2, "points": 9 },
    { "driver": "Austin Cindric", "position": 3, "points": 8 },
    { "driver": "Michael McDowell", "position": 4, "points": 7 },
    { "driver": "Ricky Stenhouse Jr", "position": 5, "points": 6 },
    { "driver": "Jamie McMurray", "position": 6, "points": 5 },
    { "driver": "Ryan Newman", "position": 7, "points": 4 },
    { "driver": "Trevor Bayne", "position": 8, "points": 3 },
    { "driver": "Kyle Busch", "position": 9, "points": 2 },
    { "driver": "Denny Hamlin", "position": 10, "points": 1 }
  ],
  "results": [
    {
      "driver": "Dale Earnhardt, Jr.",
      "position": 1,
      "pointsRace": 40,
      "lapsLed": 0,
      "penalization": 0,
      "playOffPts": 5
    },
    {
      "driver": "Kevin Harvick",
      "position": 2,
      "pointsRace": 35,
      "lapsLed": 0,
      "penalization": 0,
      "playOffPts": 0
    },
    {
      "driver": "Clint Bowyer",
      "position": 3,
      "pointsRace": 34,
      "lapsLed": 0,
      "penalization": 0,
      "playOffPts": 0
    },
    {
      "driver": "Carl Edwards",
      "position": 4,
      "pointsRace": 33,
      "lapsLed": 0,
      "penalization": 0,
      "playOffPts": 0
    },
    {
      "driver": "Tony Stewart",
      "position": 5,
      "pointsRace": 32,
      "lapsLed": 0,
      "penalization": 0,
      "playOffPts": 0
    },
    {
      "driver": "Kyle Busch",
      "position": 6,
      "pointsRace": 31,
      "lapsLed": 0,
      "penalization": 0,
      "playOffPts": 0
    },
    {
      "driver": "Austin Cindric",
      "position": 7,
      "pointsRace": 30,
      "lapsLed": 0,
      "penalization": 0,
      "playOffPts": 0
    },
    {
      "driver": "Alex Bowman",
      "position": 8,
      "pointsRace": 29,
      "lapsLed": 0,
      "penalization": 0,
      "playOffPts": 0
    },
    {
      "driver": "Kurt Busch",
      "position": 9,
      "pointsRace": 28,
      "lapsLed": 0,
      "penalization": 0,
      "playOffPts": 0
    },
    {
      "driver": "Bubba Wallace",
      "position": 10,
      "pointsRace": 27,
      "lapsLed": 0,
      "penalization": 0,
      "playOffPts": 0
    },
    {
      "driver": "Matt Kenseth",
      "position": 11,
      "pointsRace": 26,
      "lapsLed": 0,
      "penalization": 0,
      "playOffPts": 1
    },
    {
      "driver": "Ryan Blaney",
      "position": 12,
      "pointsRace": 25,
      "lapsLed": 0,
      "penalization": 0,
      "playOffPts": 0
    },
    {
      "driver": "Chase Elliott",
      "position": 13,
      "pointsRace": 24,
      "lapsLed": 0,
      "penalization": 0,
      "playOffPts": 0
    },
    {
      "driver": "A.J. Allmendinger",
      "position": 14,
      "pointsRace": 23,
      "lapsLed": 0,
      "penalization": 0,
      "playOffPts": 0
    },
    {
      "driver": "Greg Biffle",
      "position": 15,
      "pointsRace": 22,
      "lapsLed": 0,
      "penalization": 0,
      "playOffPts": 0
    },
    {
      "driver": "Chase Briscoe",
      "position": 16,
      "pointsRace": 21,
      "lapsLed": 0,
      "penalization": 0,
      "playOffPts": 0
    },
    {
      "driver": "Corey LaJoie",
      "position": 17,
      "pointsRace": 20,
      "lapsLed": 0,
      "penalization": 0,
      "playOffPts": 0
    },
    {
      "driver": "Denny Hamlin",
      "position": 18,
      "pointsRace": 19,
      "lapsLed": 0,
      "penalization": 0,
      "playOffPts": 1
    },
    {
      "driver": "Martin Truex Jr",
      "position": 19,
      "pointsRace": 18,
      "lapsLed": 0,
      "penalization": 0,
      "playOffPts": 0
    },
    {
      "driver": "Christopher Bell",
      "position": 20,
      "pointsRace": 17,
      "lapsLed": 0,
      "penalization": 0,
      "playOffPts": 0
    },
    {
      "driver": "Chris Buescher",
      "position": 21,
      "pointsRace": 16,
      "lapsLed": 0,
      "penalization": 0,
      "playOffPts": 0
    },
    {
      "driver": "Bobby Labonte",
      "position": 22,
      "pointsRace": 15,
      "lapsLed": 0,
      "penalization": 0,
      "playOffPts": 0
    },
    {
      "driver": "Mark Martin",
      "position": 23,
      "pointsRace": 14,
      "lapsLed": 0,
      "penalization": 0,
      "playOffPts": 0
    },
    {
      "driver": "Joey Logano",
      "position": 24,
      "pointsRace": 13,
      "lapsLed": 0,
      "penalization": 0,
      "playOffPts": 0
    },
    {
      "driver": "Michael McDowell",
      "position": 25,
      "pointsRace": 12,
      "lapsLed": 0,
      "penalization": 0,
      "playOffPts": 0
    },
    {
      "driver": "Elliott Sadler",
      "position": 26,
      "pointsRace": 11,
      "lapsLed": 0,
      "penalization": 0,
      "playOffPts": 0
    },
    {
      "driver": "Paul Menard",
      "position": 27,
      "pointsRace": 10,
      "lapsLed": 0,
      "penalization": 0,
      "playOffPts": 0
    },
    {
      "driver": "Jeff Burton",
      "position": 28,
      "pointsRace": 9,
      "lapsLed": 0,
      "penalization": 0,
      "playOffPts": 0
    },
    {
      "driver": "Jamie McMurray",
      "position": 29,
      "pointsRace": 8,
      "lapsLed": 0,
      "penalization": 0,
      "playOffPts": 0
    },
    {
      "driver": "Kyle Larson",
      "position": 30,
      "pointsRace": 7,
      "lapsLed": 0,
      "penalization": 0,
      "playOffPts": 0
    },
    {
      "driver": "Ricky Stenhouse Jr",
      "position": 31,
      "pointsRace": 6,
      "lapsLed": 0,
      "penalization": 0,
      "playOffPts": 0
    },
    {
      "driver": "David Ragan",
      "position": 32,
      "pointsRace": 5,
      "lapsLed": 0,
      "penalization": 0,
      "playOffPts": 0
    },
    {
      "driver": "Juan Pablo Montoya",
      "position": 33,
      "pointsRace": 4,
      "lapsLed": 0,
      "penalization": 0,
      "playOffPts": 0
    },
    {
      "driver": "William Byron",
      "position": 34,
      "pointsRace": 3,
      "lapsLed": 0,
      "penalization": 0,
      "playOffPts": 0
    },
    {
      "driver": "David Reutimann",
      "position": 35,
      "pointsRace": 2,
      "lapsLed": 0,
      "penalization": 0,
      "playOffPts": 0
    },
    {
      "driver": "John H. Nemechek",
      "position": 36,
      "pointsRace": 1,
      "lapsLed": 0,
      "penalization": 0,
      "playOffPts": 0
    },
    {
      "driver": "Reed Sorenson",
      "position": 37,
      "pointsRace": 1,
      "lapsLed": 0,
      "penalization": 0,
      "playOffPts": 0
    },
    {
      "driver": "Brad Keselowski",
      "position": 38,
      "pointsRace": 1,
      "lapsLed": 0,
      "penalization": 0,
      "playOffPts": 0
    },
    {
      "driver": "Riley Herbst",
      "position": 39,
      "pointsRace": 1,
      "lapsLed": 0,
      "penalization": 0,
      "playOffPts": 0
    },
    {
      "driver": "Daniel Suarez",
      "position": 40,
      "pointsRace": 1,
      "lapsLed": 0,
      "penalization": 0,
      "playOffPts": 0
    }
  ]
}
